fenapack/SubfieldBC.h
fenapack/__init__.py
fenapack/_field_split_utils.py
fenapack/assembling.py
fenapack/field_split.py
fenapack/field_split_backend.py
fenapack/nonlinear_solvers.py
fenapack/petsc_casters.h
fenapack/preconditioners.py
fenapack/stabilization.py
fenapack/utils.py
fenapack-2019.1.0.data/data/share/fenapack/demo/data/mesh_lshape.xml
fenapack-2019.1.0.data/data/share/fenapack/demo/defcon/navier-stokes.py
fenapack-2019.1.0.data/data/share/fenapack/demo/defcon/mesh/genmesh.py
fenapack-2019.1.0.data/data/share/fenapack/demo/navier-stokes-pcd/demo_navier-stokes-pcd.py
fenapack-2019.1.0.data/data/share/fenapack/demo/navier-stokes-pcd/documentation.rst
fenapack-2019.1.0.data/data/share/fenapack/demo/unsteady-navier-stokes-pcd/demo_unsteady-navier-stokes-pcd.py
fenapack-2019.1.0.data/data/share/fenapack/demo/unsteady-navier-stokes-pcd/demo_unsteady-navier-stokes-pcdr.py
fenapack-2019.1.0.data/data/share/fenapack/demo/unsteady-navier-stokes-pcd/documentation.rst
fenapack-2019.1.0.dist-info/METADATA
fenapack-2019.1.0.dist-info/RECORD
fenapack-2019.1.0.dist-info/WHEEL
fenapack-2019.1.0.dist-info/top_level.txt
