Metadata-Version: 2.1
Name: fenapack
Version: 2019.1.0
Summary: FENaPack: FEniCS Navier-Stokes preconditioning package
Home-page: https://github.com/blechta/fenapack
Author: Jan Blechta
Author-email: blechta@karlin.mff.cuni.cz
License: UNKNOWN
Platform: UNKNOWN
Classifier: Development Status :: 2 - Pre-Alpha
Classifier: Environment :: Console
Classifier: Intended Audience :: Science/Research
Classifier: License :: OSI Approved :: GNU Lesser General Public License v3 or later (LGPLv3+)
Classifier: Programming Language :: Python :: 3
Classifier: Programming Language :: C++
Classifier: Topic :: Scientific/Engineering :: Mathematics
